{"version":1,"resource":"file:///home/karthi/ml/photo.py","entries":[{"id":"EpIB.py","source":"textFileCreate.source","timestamp":1720607177913},{"id":"plMf.py","timestamp":1720607801200},{"id":"JhO7.py","timestamp":1720607908167},{"id":"aoxb.py","timestamp":1720607928317},{"id":"h73I.py","timestamp":1720614527224},{"id":"ZIrM.py","timestamp":1720614568044},{"id":"dGsc.py","timestamp":1720614955140},{"id":"Eq3J.py","timestamp":1720614965147},{"id":"gtol.py","timestamp":1720615634784},{"id":"kqFR.py","timestamp":1720757152713}]}